setup.py
binormal_distributions/Binomialdistribution.py
binormal_distributions/Gaussiandistribution.py
binormal_distributions/Generaldistribution.py
binormal_distributions/__init__.py
binormal_distributions.egg-info/PKG-INFO
binormal_distributions.egg-info/SOURCES.txt
binormal_distributions.egg-info/dependency_links.txt
binormal_distributions.egg-info/not-zip-safe
binormal_distributions.egg-info/top_level.txt