Metadata-Version: 1.0
Name: binormal-distributions
Version: 0.1
Summary: Gaussian and binomial distributions
Home-page: UNKNOWN
Author: Tharun Ragulan
Author-email: UNKNOWN
License: UNKNOWN
Platform: UNKNOWN
